Workbook

Sheet Cost List
A1: Bargain Bay - Cost List
A2: Fill the yellow cells. One row per bill, amount BEFORE tax (HST is recovered, so it is not a cost). Do NOT list wages, truck day rates or fuel - the daily P&L already counts those from clock-ins and dispatch. Row 9 is an example: overwrite it.
A3: Check cost on this date: | B3: 46303
A4: Overhead on that date ($) | B4: =SUM(H9:H68) | C4: Each bill spread over the days it covers: a month's days add back to the bill. Matches the app.
A5: Average per day ($) | B5: =SUM(I9:I68) | C5: Smooth average (monthly x 12 / 365). One-time costs are excluded here and only count on their own date.
A6: Average per month ($) | B6: =B5*365/12
A8: Cost | B8: Category | C8: Amount before tax ($) | D8: Billed | E8: Starts (or the date, if one time) | F8: Ends (optional) | G8: Note | H8: Cost on chosen date ($) | I8: Average per day ($)
A9: EXAMPLE - Rent (overwrite me) | B9: Rent | C9: 1000 | D9: Monthly | E9: 46296 | G9: Example figure only, not our real rent | H9: =IF(OR(C9="",D9="",E9=""),0,IF(OR($B$3<E9,AND(F9<>"",$B$3>F9)),0,CHOOSE(MATCH(D9,Lists!$B$2:$B$7,0),C9,C9/7,C9/DAY(EOMONTH($B$3,0)),C9/(EDATE(DATE(YEAR($B$3),3*INT((MONTH($B$3)-1)/3)+1,1),3)-DATE(YEAR($B$3),3*INT((MONTH($B$3)-1)/3)+1,1)),C9/(DATE(YEAR($B$3)+1,1,1)-DATE(YEAR($B$3),1,1)),IF($B$3=E9,C9,0)))) | I9: =IF(OR(C9="",D9=""),0,CHOOSE(MATCH(D9,Lists!$B$2:$B$7,0),C9,C9/7,C9*12/365,C9*4/365,C9/365,0))
H10: =IF(OR(C10="",D10="",E10=""),0,IF(OR($B$3<E10,AND(F10<>"",$B$3>F10)),0,CHOOSE(MATCH(D10,Lists!$B$2:$B$7,0),C10,C10/7,C10/DAY(EOMONTH($B$3,0)),C10/(EDATE(DATE(YEAR($B$3),3*INT((MONTH($B$3)-1)/3)+1,1),3)-DATE(YEAR($B$3),3*INT((MONTH($B$3)-1)/3)+1,1)),C10/(DATE(YEAR($B$3)+1,1,1)-DATE(YEAR($B$3),1,1)),IF($B$3=E10,C10,0)))) | I10: =IF(OR(C10="",D10=""),0,CHOOSE(MATCH(D10,Lists!$B$2:$B$7,0),C10,C10/7,C10*12/365,C10*4/365,C10/365,0))
H11: =IF(OR(C11="",D11="",E11=""),0,IF(OR($B$3<E11,AND(F11<>"",$B$3>F11)),0,CHOOSE(MATCH(D11,Lists!$B$2:$B$7,0),C11,C11/7,C11/DAY(EOMONTH($B$3,0)),C11/(EDATE(DATE(YEAR($B$3),3*INT((MONTH($B$3)-1)/3)+1,1),3)-DATE(YEAR($B$3),3*INT((MONTH($B$3)-1)/3)+1,1)),C11/(DATE(YEAR($B$3)+1,1,1)-DATE(YEAR($B$3),1,1)),IF($B$3=E11,C11,0)))) | I11: =IF(OR(C11="",D11=""),0,CHOOSE(MATCH(D11,Lists!$B$2:$B$7,0),C11,C11/7,C11*12/365,C11*4/365,C11/365,0))
H12: =IF(OR(C12="",D12="",E12=""),0,IF(OR($B$3<E12,AND(F12<>"",$B$3>F12)),0,CHOOSE(MATCH(D12,Lists!$B$2:$B$7,0),C12,C12/7,C12/DAY(EOMONTH($B$3,0)),C12/(EDATE(DATE(YEAR($B$3),3*INT((MONTH($B$3)-1)/3)+1,1),3)-DATE(YEAR($B$3),3*INT((MONTH($B$3)-1)/3)+1,1)),C12/(DATE(YEAR($B$3)+1,1,1)-DATE(YEAR($B$3),1,1)),IF($B$3=E12,C12,0)))) | I12: =IF(OR(C12="",D12=""),0,CHOOSE(MATCH(D12,Lists!$B$2:$B$7,0),C12,C12/7,C12*12/365,C12*4/365,C12/365,0))
H13: =IF(OR(C13="",D13="",E13=""),0,IF(OR($B$3<E13,AND(F13<>"",$B$3>F13)),0,CHOOSE(MATCH(D13,Lists!$B$2:$B$7,0),C13,C13/7,C13/DAY(EOMONTH($B$3,0)),C13/(EDATE(DATE(YEAR($B$3),3*INT((MONTH($B$3)-1)/3)+1,1),3)-DATE(YEAR($B$3),3*INT((MONTH($B$3)-1)/3)+1,1)),C13/(DATE(YEAR($B$3)+1,1,1)-DATE(YEAR($B$3),1,1)),IF($B$3=E13,C13,0)))) | I13: =IF(OR(C13="",D13=""),0,CHOOSE(MATCH(D13,Lists!$B$2:$B$7,0),C13,C13/7,C13*12/365,C13*4/365,C13/365,0))
H14: =IF(OR(C14="",D14="",E14=""),0,IF(OR($B$3<E14,AND(F14<>"",$B$3>F14)),0,CHOOSE(MATCH(D14,Lists!$B$2:$B$7,0),C14,C14/7,C14/DAY(EOMONTH($B$3,0)),C14/(EDATE(DATE(YEAR($B$3),3*INT((MONTH($B$3)-1)/3)+1,1),3)-DATE(YEAR($B$3),3*INT((MONTH($B$3)-1)/3)+1,1)),C14/(DATE(YEAR($B$3)+1,1,1)-DATE(YEAR($B$3),1,1)),IF($B$3=E14,C14,0)))) | I14: =IF(OR(C14="",D14=""),0,CHOOSE(MATCH(D14,Lists!$B$2:$B$7,0),C14,C14/7,C14*12/365,C14*4/365,C14/365,0))
H15: =IF(OR(C15="",D15="",E15=""),0,IF(OR($B$3<E15,AND(F15<>"",$B$3>F15)),0,CHOOSE(MATCH(D15,Lists!$B$2:$B$7,0),C15,C15/7,C15/DAY(EOMONTH($B$3,0)),C15/(EDATE(DATE(YEAR($B$3),3*INT((MONTH($B$3)-1)/3)+1,1),3)-DATE(YEAR($B$3),3*INT((MONTH($B$3)-1)/3)+1,1)),C15/(DATE(YEAR($B$3)+1,1,1)-DATE(YEAR($B$3),1,1)),IF($B$3=E15,C15,0)))) | I15: =IF(OR(C15="",D15=""),0,CHOOSE(MATCH(D15,Lists!$B$2:$B$7,0),C15,C15/7,C15*12/365,C15*4/365,C15/365,0))
H16: =IF(OR(C16="",D16="",E16=""),0,IF(OR($B$3<E16,AND(F16<>"",$B$3>F16)),0,CHOOSE(MATCH(D16,Lists!$B$2:$B$7,0),C16,C16/7,C16/DAY(EOMONTH($B$3,0)),C16/(EDATE(DATE(YEAR($B$3),3*INT((MONTH($B$3)-1)/3)+1,1),3)-DATE(YEAR($B$3),3*INT((MONTH($B$3)-1)/3)+1,1)),C16/(DATE(YEAR($B$3)+1,1,1)-DATE(YEAR($B$3),1,1)),IF($B$3=E16,C16,0)))) | I16: =IF(OR(C16="",D16=""),0,CHOOSE(MATCH(D16,Lists!$B$2:$B$7,0),C16,C16/7,C16*12/365,C16*4/365,C16/365,0))
H17: =IF(OR(C17="",D17="",E17=""),0,IF(OR($B$3<E17,AND(F17<>"",$B$3>F17)),0,CHOOSE(MATCH(D17,Lists!$B$2:$B$7,0),C17,C17/7,C17/DAY(EOMONTH($B$3,0)),C17/(EDATE(DATE(YEAR($B$3),3*INT((MONTH($B$3)-1)/3)+1,1),3)-DATE(YEAR($B$3),3*INT((MONTH($B$3)-1)/3)+1,1)),C17/(DATE(YEAR($B$3)+1,1,1)-DATE(YEAR($B$3),1,1)),IF($B$3=E17,C17,0)))) | I17: =IF(OR(C17="",D17=""),0,CHOOSE(MATCH(D17,Lists!$B$2:$B$7,0),C17,C17/7,C17*12/365,C17*4/365,C17/365,0))
H18: =IF(OR(C18="",D18="",E18=""),0,IF(OR($B$3<E18,AND(F18<>"",$B$3>F18)),0,CHOOSE(MATCH(D18,Lists!$B$2:$B$7,0),C18,C18/7,C18/DAY(EOMONTH($B$3,0)),C18/(EDATE(DATE(YEAR($B$3),3*INT((MONTH($B$3)-1)/3)+1,1),3)-DATE(YEAR($B$3),3*INT((MONTH($B$3)-1)/3)+1,1)),C18/(DATE(YEAR($B$3)+1,1,1)-DATE(YEAR($B$3),1,1)),IF($B$3=E18,C18,0)))) | I18: =IF(OR(C18="",D18=""),0,CHOOSE(MATCH(D18,Lists!$B$2:$B$7,0),C18,C18/7,C18*12/365,C18*4/365,C18/365,0))
H19: =IF(OR(C19="",D19="",E19=""),0,IF(OR($B$3<E19,AND(F19<>"",$B$3>F19)),0,CHOOSE(MATCH(D19,Lists!$B$2:$B$7,0),C19,C19/7,C19/DAY(EOMONTH($B$3,0)),C19/(EDATE(DATE(YEAR($B$3),3*INT((MONTH($B$3)-1)/3)+1,1),3)-DATE(YEAR($B$3),3*INT((MONTH($B$3)-1)/3)+1,1)),C19/(DATE(YEAR($B$3)+1,1,1)-DATE(YEAR($B$3),1,1)),IF($B$3=E19,C19,0)))) | I19: =IF(OR(C19="",D19=""),0,CHOOSE(MATCH(D19,Lists!$B$2:$B$7,0),C19,C19/7,C19*12/365,C19*4/365,C19/365,0))
H20: =IF(OR(C20="",D20="",E20=""),0,IF(OR($B$3<E20,AND(F20<>"",$B$3>F20)),0,CHOOSE(MATCH(D20,Lists!$B$2:$B$7,0),C20,C20/7,C20/DAY(EOMONTH($B$3,0)),C20/(EDATE(DATE(YEAR($B$3),3*INT((MONTH($B$3)-1)/3)+1,1),3)-DATE(YEAR($B$3),3*INT((MONTH($B$3)-1)/3)+1,1)),C20/(DATE(YEAR($B$3)+1,1,1)-DATE(YEAR($B$3),1,1)),IF($B$3=E20,C20,0)))) | I20: =IF(OR(C20="",D20=""),0,CHOOSE(MATCH(D20,Lists!$B$2:$B$7,0),C20,C20/7,C20*12/365,C20*4/365,C20/365,0))
H21: =IF(OR(C21="",D21="",E21=""),0,IF(OR($B$3<E21,AND(F21<>"",$B$3>F21)),0,CHOOSE(MATCH(D21,Lists!$B$2:$B$7,0),C21,C21/7,C21/DAY(EOMONTH($B$3,0)),C21/(EDATE(DATE(YEAR($B$3),3*INT((MONTH($B$3)-1)/3)+1,1),3)-DATE(YEAR($B$3),3*INT((MONTH($B$3)-1)/3)+1,1)),C21/(DATE(YEAR($B$3)+1,1,1)-DATE(YEAR($B$3),1,1)),IF($B$3=E21,C21,0)))) | I21: =IF(OR(C21="",D21=""),0,CHOOSE(MATCH(D21,Lists!$B$2:$B$7,0),C21,C21/7,C21*12/365,C21*4/365,C21/365,0))
... H68: =IF(OR(C68="",D68="",E68=""),0,IF(OR($B$3<E68,AND(F68<>"",$B$3>F68)),0,CHOOSE(MATCH(D68,Lists!$B$2:$B$7,0),C68,C68/7,C68/DAY(EOMONTH($B$3,0)),C68/(EDATE(DATE(YEAR($B$3),3*INT((MONTH($B$3)-1)/3)+1,1),3)-DATE(YEAR($B$3),3*INT((MONTH($B$3)-1)/3)+1,1)),C68/(DATE(YEAR($B$3)+1,1,1)-DATE(YEAR($B$3),1,1)),IF($B$3=E68,C68,0)))) | I68: =IF(OR(C68="",D68=""),0,CHOOSE(MATCH(D68,Lists!$B$2:$B$7,0),C68,C68/7,C68*12/365,C68*4/365,C68/365,0))

Sheet Lists
A1: Category | B1: Billed
A2: Rent | B2: Every day
A3: Utilities | B3: Weekly
A4: Insurance | B4: Monthly
A5: Software | B5: Quarterly
A6: Truck (lease, plates, upkeep) | B6: Yearly
A7: Advertising | B7: One time
A8: Card & bank fees
A9: Loan & interest
A10: Other
